homodyne/.coveragerc
homodyne/__init__.py
homodyne/_version.py
homodyne/py.typed
homodyne/analysis/__init__.py
homodyne/analysis/core.py
homodyne/analysis/helpers.py
homodyne/cli/__init__.py
homodyne/cli/core.py
homodyne/cli/create_config.py
homodyne/cli/enhanced_runner.py
homodyne/cli/import_manager.py
homodyne/cli/optimization.py
homodyne/cli/parser.py
homodyne/cli/run_homodyne.py
homodyne/cli/simulation.py
homodyne/cli/utils.py
homodyne/cli/visualization.py
homodyne/config/__init__.py
homodyne/config/laminar_flow.json
homodyne/config/static_anisotropic.json
homodyne/config/static_isotropic.json
homodyne/config/template.json
homodyne/config/update_solver_configs.py
homodyne/core/__init__.py
homodyne/core/analysis.py
homodyne/core/blas_kernels.py
homodyne/core/caching.py
homodyne/core/composed_analysis.py
homodyne/core/composition.py
homodyne/core/config.py
homodyne/core/cpu_optimization.py
homodyne/core/initialization_optimizer.py
homodyne/core/io_utils.py
homodyne/core/kernels.py
homodyne/core/lazy_imports.py
homodyne/core/mathematical_optimization.py
homodyne/core/optimization_utils.py
homodyne/core/performance_analytics.py
homodyne/core/result_memoization.py
homodyne/core/secure_io.py
homodyne/core/security_metrics.py
homodyne/core/security_performance.py
homodyne/core/workflows.py
homodyne/data/__init__.py
homodyne/data/xpcs_loader.py
homodyne/optimization/__init__.py
homodyne/optimization/blas_optimization.py
homodyne/optimization/classical.py
homodyne/optimization/distributed.py
homodyne/optimization/ml_acceleration.py
homodyne/optimization/robust.py
homodyne/optimization/utils.py
homodyne/performance/__init__.py
homodyne/performance/baseline.py
homodyne/performance/cpu_profiling.py
homodyne/performance/integrated_monitoring.py
homodyne/performance/monitoring.py
homodyne/performance/regression_prevention.py
homodyne/performance/simple_monitoring.py
homodyne/performance/startup_monitoring.py
homodyne/statistics/__init__.py
homodyne/statistics/chi_squared.py
homodyne_analysis-1.0.1.dist-info/licenses/LICENSE
homodyne_analysis-1.0.1.dist-info/METADATA
homodyne_analysis-1.0.1.dist-info/WHEEL
homodyne_analysis-1.0.1.dist-info/entry_points.txt
homodyne_analysis-1.0.1.dist-info/top_level.txt
homodyne_analysis-1.0.1.dist-info/RECORD
