Metadata-Version: 2.4
Name: homodyne-analysis
Version: 1.0.1
Summary: High-performance Python package for analyzing homodyne scattering in X-ray Photon Correlation Spectroscopy (XPCS) with frame counting fixes (v1.0.0+) and conditional angle subsampling for preserving angular information
Author: Hongrui He
Author-email: Wei Chen <wchen@anl.gov>
Maintainer-email: Wei Chen <wchen@anl.gov>
License: MIT License
Project-URL: Homepage, https://github.com/imewei/homodyne
Project-URL: Documentation, https://homodyne-analysis.readthedocs.io
Project-URL: Repository, https://github.com/imewei/homodyne
Project-URL: Issues, https://github.com/imewei/homodyne/issues
Project-URL: Changelog, https://github.com/imewei/homodyne/blob/main/CHANGELOG.md
Keywords: xpcs,homodyne,scattering,correlation,spectroscopy,scientific-computing,physics,materials-science
Classifier: Development Status :: 5 - Production/Stable
Classifier: Intended Audience :: Science/Research
Classifier: License :: OSI Approved :: MIT License
Classifier: Operating System :: OS Independent
Classifier: Programming Language :: Python :: 3
Classifier: Programming Language :: Python :: 3.12
Classifier: Programming Language :: Python :: 3.13
Classifier: Programming Language :: Python :: 3.14
Classifier: Topic :: Scientific/Engineering :: Physics
Classifier: Topic :: Scientific/Engineering :: Information Analysis
Classifier: Typing :: Typed
Requires-Python: >=3.12
License-File: LICENSE
Requires-Dist: numpy>=2.3.3
Requires-Dist: scipy>=1.16.2
Requires-Dist: matplotlib>=3.10.6
Requires-Dist: h5py>=3.14.0
Requires-Dist: pydantic>=2.11.9
Requires-Dist: typer>=0.19.2
Requires-Dist: rich>=14.1.0
Requires-Dist: typing-extensions>=4.12.0; python_version < "3.13"
Provides-Extra: performance
Requires-Dist: numba>=0.62.1; extra == "performance"
Requires-Dist: psutil>=6.0.0; extra == "performance"
Requires-Dist: numexpr>=2.10.0; extra == "performance"
Requires-Dist: bottleneck>=1.4.0; extra == "performance"
Requires-Dist: threadpoolctl>=3.5.0; extra == "performance"
Requires-Dist: py-cpuinfo>=9.0.0; extra == "performance"
Requires-Dist: cachetools>=5.5.0; extra == "performance"
Requires-Dist: joblib>=1.4.0; extra == "performance"
Provides-Extra: robust
Requires-Dist: cvxpy>=1.7.3; extra == "robust"
Requires-Dist: gurobipy>=11.0.0; extra == "robust"
Requires-Dist: mosek>=10.2.0; extra == "robust"
Provides-Extra: test
Requires-Dist: pytest>=8.4.2; extra == "test"
Requires-Dist: pytest-cov>=7.0.0; extra == "test"
Requires-Dist: pytest-xdist>=3.8.0; extra == "test"
Requires-Dist: pytest-benchmark>=5.1.0; extra == "test"
Requires-Dist: pytest-timeout>=2.3.0; extra == "test"
Requires-Dist: pytest-mock>=3.15.1; extra == "test"
Requires-Dist: pytest-html>=4.1.1; extra == "test"
Requires-Dist: pytest-json-report>=1.5.0; extra == "test"
Requires-Dist: pytest-metadata>=3.1.0; extra == "test"
Requires-Dist: pytest-randomly>=3.16.0; extra == "test"
Requires-Dist: pytest-repeat>=0.9.3; extra == "test"
Requires-Dist: pytest-picked>=0.5.0; extra == "test"
Requires-Dist: pytest-clarity>=1.0.1; extra == "test"
Requires-Dist: pytest-sugar>=1.0.0; extra == "test"
Requires-Dist: pytest-instafail>=0.5.0; extra == "test"
Requires-Dist: hypothesis>=6.112.0; extra == "test"
Requires-Dist: faker>=30.0.0; extra == "test"
Requires-Dist: factory-boy>=3.3.0; extra == "test"
Requires-Dist: freezegun>=1.5.0; extra == "test"
Requires-Dist: responses>=0.25.0; extra == "test"
Requires-Dist: memory-profiler>=0.61.0; extra == "test"
Requires-Dist: py-spy>=0.3.14; extra == "test"
Requires-Dist: scalene>=1.5.0; extra == "test"
Requires-Dist: nbval>=0.10.0; extra == "test"
Requires-Dist: jupyter>=1.0.0; extra == "test"
Requires-Dist: pydantic>=2.5.0; extra == "test"
Provides-Extra: quality
Requires-Dist: ruff>=0.13.2; extra == "quality"
Requires-Dist: black>=25.9.0; extra == "quality"
Requires-Dist: isort>=6.1.0; extra == "quality"
Requires-Dist: mypy>=1.18.2; extra == "quality"
Requires-Dist: bandit>=1.8.6; extra == "quality"
Requires-Dist: safety>=3.6.2; extra == "quality"
Requires-Dist: pip-audit>=2.7.0; extra == "quality"
Requires-Dist: pre-commit>=4.0.0; extra == "quality"
Requires-Dist: vulture>=2.13; extra == "quality"
Requires-Dist: interrogate>=1.7.0; extra == "quality"
Requires-Dist: flake8>=7.3.0; extra == "quality"
Provides-Extra: dev
Requires-Dist: homodyne-analysis[docs,performance,quality,test]; extra == "dev"
Requires-Dist: pre-commit>=3.5.0; extra == "dev"
Requires-Dist: build>=1.0.0; extra == "dev"
Requires-Dist: twine>=4.0.0; extra == "dev"
Requires-Dist: pip-tools>=7.0.0; extra == "dev"
Requires-Dist: tox>=4.11.0; extra == "dev"
Requires-Dist: nox>=2023.4.22; extra == "dev"
Provides-Extra: docs
Requires-Dist: sphinx>=8.2.0; extra == "docs"
Requires-Dist: sphinx-rtd-theme>=3.0.2; extra == "docs"
Requires-Dist: sphinx-autodoc-typehints>=3.2.0; extra == "docs"
Requires-Dist: myst-parser>=4.0.0; extra == "docs"
Requires-Dist: sphinx-copybutton>=0.5.2; extra == "docs"
Requires-Dist: sphinx-design>=0.6.0; extra == "docs"
Requires-Dist: sphinx-autoapi>=3.4.0; extra == "docs"
Requires-Dist: numpydoc>=1.9.0; extra == "docs"
Requires-Dist: sphinx-gallery>=0.18.0; extra == "docs"
Requires-Dist: linkify-it-py>=2.0.0; extra == "docs"
Provides-Extra: all
Requires-Dist: homodyne-analysis[dev,docs,performance,quality,robust,test]; extra == "all"
Provides-Extra: cpu-optimized
Requires-Dist: homodyne-analysis[performance]; extra == "cpu-optimized"
Requires-Dist: cachetools>=5.3.0; extra == "cpu-optimized"
Requires-Dist: joblib>=1.3.0; extra == "cpu-optimized"
Requires-Dist: multiprocessing-logging>=0.3.4; extra == "cpu-optimized"
Dynamic: license-file
